README.md
setup.py
tests/__init__.py
tests/test_base64url.py
tests/test_math.py
tests/test_strings.py
tests/oop/__init__.py
tests/oop/test_borg.py
tests/oop/test_cache.py
tests/time/__init__.py
tests/time/test_formatter.py
tests/time/test_tzconversion.py
zaach/__init__.py
zaach/base64url.py
zaach/math.py
zaach/strings.py
zaach.egg-info/PKG-INFO
zaach.egg-info/SOURCES.txt
zaach.egg-info/dependency_links.txt
zaach.egg-info/top_level.txt
zaach/oop/__init__.py
zaach/oop/borg.py
zaach/oop/cache.py
zaach/time/__init__.py
zaach/time/formatter.py
zaach/time/tzconversion.py