Metadata-Version: 1.0
Name: zaach
Version: 1.0.10
Summary: A collection of helpers
Home-page: https://bitbucket.org/fabian/zaach
Author: Fabian Topfstedt
Author-email: UNKNOWN
License: The MIT Licence
Keywords: base64url,timezone,conversion,math
Platform: UNKNOWN
